odoo/addons/sale_coupon_order_suggestion/README.rst
odoo/addons/sale_coupon_order_suggestion/__init__.py
odoo/addons/sale_coupon_order_suggestion/__manifest__.py
odoo/addons/sale_coupon_order_suggestion/i18n/sale_coupon_order_suggestion.pot
odoo/addons/sale_coupon_order_suggestion/models/__init__.py
odoo/addons/sale_coupon_order_suggestion/models/sale_order.py
odoo/addons/sale_coupon_order_suggestion/readme/CONTRIBUTORS.rst
odoo/addons/sale_coupon_order_suggestion/readme/DESCRIPTION.rst
odoo/addons/sale_coupon_order_suggestion/readme/USAGE.rst
odoo/addons/sale_coupon_order_suggestion/static/description/icon.png
odoo/addons/sale_coupon_order_suggestion/static/description/index.html
odoo/addons/sale_coupon_order_suggestion/static/src/js/suggest_promotion_widget.esm.js
odoo/addons/sale_coupon_order_suggestion/static/src/js/suggest_promotion_widget_owl.esm.js
odoo/addons/sale_coupon_order_suggestion/static/src/xml/suggest_promotion.xml
odoo/addons/sale_coupon_order_suggestion/views/sale_order_views.xml
odoo_addon_sale_coupon_order_suggestion-15.0.1.0.0.3.dist-info/METADATA
odoo_addon_sale_coupon_order_suggestion-15.0.1.0.0.3.dist-info/WHEEL
odoo_addon_sale_coupon_order_suggestion-15.0.1.0.0.3.dist-info/top_level.txt
odoo_addon_sale_coupon_order_suggestion-15.0.1.0.0.3.dist-info/RECORD
